{"rawText":"JOHN DEVELOPER\r\njohn.developer@email.com | (555) 123-4567 | San Francisco, CA\r\nlinkedin.com/in/johndeveloper | github.com/johndeveloper\r\n\r\nPROFESSIONAL SUMMARY\r\nPassionate full-stack engineer with 8+ years of experience building scalable web applications. Expert in React, Node.js, and cloud architecture. Led cross-functional teams to deliver products used by millions of users. Strong advocate for clean code and test-driven development.\r\n\r\nEXPERIENCE\r\n\r\nSenior Software Engineer\r\nTechCorp Inc., San Francisco, CA\r\nJanuary 2020 - Present\r\n• Architected and built microservices platform serving 10M+ daily users\r\n• Led team of 5 engineers to deliver new payment processing system\r\n• Reduced API response times by 60% through caching strategies\r\n• Mentored junior developers and established coding standards\r\n\r\nSoftware Engineer\r\nStartupXYZ, Austin, TX\r\nJune 2017 - December 2019\r\n• Built React frontend for B2B SaaS product with 500+ enterprise clients\r\n• Implemented GraphQL API reducing frontend data fetching complexity\r\n• Set up CI/CD pipeline with GitHub Actions and AWS\r\n\r\nJunior Developer\r\nWebAgency LLC, Seattle, WA\r\nAugust 2015 - May 2017\r\n• Developed responsive websites for Fortune 500 clients\r\n• Created reusable component library used across 20+ projects\r\n\r\nEDUCATION\r\n\r\nBachelor of Science in Computer Science\r\nUniversity of Washington, Seattle, WA\r\n2011 - 2015\r\n\r\nSKILLS\r\nJavaScript, TypeScript, React, Node.js, Python, PostgreSQL, MongoDB, AWS, Docker, Kubernetes, GraphQL, REST APIs\r\n\r\nPROJECTS\r\n\r\nPersonal Finance Tracker\r\nA React Native app helping users track expenses and budgets\r\nTechnologies: React Native, Firebase, Redux\r\n\r\nOpen Source CLI Tool\r\nCommand-line tool for automating development workflows\r\nTechnologies: Node.js, TypeScript, npm","mimeType":"text/plain","contact":{"firstName":"John","lastName":"Developer","email":"john.developer@email.com","phone":"(555) 123-4567","linkedin":"linkedin.com/in/johndeveloper","location":"San Francisco, CA","github":"github.com/johndeveloper"},"experience":[{"title":"Senior Software Engineer","company":"TechCorp Inc.","description":"• Architected and built microservices platform serving 10M+ daily users\n• Led team of 5 engineers to deliver new payment processing system\n• Reduced API response times by 60% through caching strategies\n• Mentored junior developers and established coding standards","bullets":["Architected and built microservices platform serving 10M+ daily users","Led team of 5 engineers to deliver new payment processing system","Reduced API response times by 60% through caching strategies","Mentored junior developers and established coding standards"],"location":"San Francisco, CA","startDate":"Jan 2020","endDate":"Present","current":true},{"title":"Software Engineer","company":"StartupXYZ","description":"• Built React frontend for B2B SaaS product with 500+ enterprise clients\n• Implemented GraphQL API reducing frontend data fetching complexity\n• Set up CI/CD pipeline with GitHub Actions and AWS","bullets":["Built React frontend for B2B SaaS product with 500+ enterprise clients","Implemented GraphQL API reducing frontend data fetching complexity","Set up CI/CD pipeline with GitHub Actions and AWS"],"location":"Austin, TX","startDate":"Jun 2017","endDate":"Dec 2019","current":false},{"title":"Junior Developer","company":"WebAgency LLC","description":"• Developed responsive websites for Fortune 500 clients\n• Created reusable component library used across 20+ projects","bullets":["Developed responsive websites for Fortune 500 clients","Created reusable component library used across 20+ projects"],"location":"Seattle, WA","startDate":"Aug 2015","endDate":"May 2017","current":false}],"education":[{"institution":"University of Washington","degree":"Bachelor of Science","fieldOfStudy":"Computer Science","startDate":"2011","endDate":"2015"}],"skills":["JavaScript","TypeScript","React","Node.js","Python","PostgreSQL","MongoDB","AWS","Docker","Kubernetes","GraphQL","REST APIs"],"projects":[{"name":"Personal Finance Tracker","description":"A React Native app helping users track expenses and budgets","technologies":["React Native","Firebase","Redux"]},{"name":"Open Source CLI Tool","description":"Command-line tool for automating development workflows","technologies":["Node.js","TypeScript","npm"]}]}